{
  "project_info": {
    "project_number": "380175794447",
    "project_id": "fir-android-a45ad",
    "storage_bucket": "fir-android-a45ad.firebasestorage.app"
  },
  "client": [
    {
      "client_info": {
        "mobilesdk_app_id": "1:380175794447:android:1ce22aecbcfbefd708fe7a",
        "android_client_info": {
          "package_name": "com.blaise.firebase"
        }
      },
      "oauth_client": [],
      "api_key": [
        {
          "current_key": "AIzaSyBgPi4TDt7ZyHHvxkW50Wh0jSw-DVNUpzY"
        }
      ],
      "services": {
        "appinvite_service": {
          "other_platform_oauth_client": []
        }
      }
    }
  ],
  "configuration_version": "1"
}